odoo8_addon_stock_inventory_discrepancy-8.0.1.0.0.99.dev2-py2.7-nspkg.pth
odoo8_addon_stock_inventory_discrepancy-8.0.1.0.0.99.dev2.dist-info/METADATA
odoo8_addon_stock_inventory_discrepancy-8.0.1.0.0.99.dev2.dist-info/RECORD
odoo8_addon_stock_inventory_discrepancy-8.0.1.0.0.99.dev2.dist-info/WHEEL
odoo8_addon_stock_inventory_discrepancy-8.0.1.0.0.99.dev2.dist-info/namespace_packages.txt
odoo8_addon_stock_inventory_discrepancy-8.0.1.0.0.99.dev2.dist-info/top_level.txt
odoo_addons/stock_inventory_discrepancy/README.rst
odoo_addons/stock_inventory_discrepancy/__init__.py
odoo_addons/stock_inventory_discrepancy/__openerp__.py
odoo_addons/stock_inventory_discrepancy/i18n/de.po
odoo_addons/stock_inventory_discrepancy/i18n/es.po
odoo_addons/stock_inventory_discrepancy/i18n/es_ES.po
odoo_addons/stock_inventory_discrepancy/i18n/fr.po
odoo_addons/stock_inventory_discrepancy/i18n/fr_FR.po
odoo_addons/stock_inventory_discrepancy/i18n/it.po
odoo_addons/stock_inventory_discrepancy/i18n/nl.po
odoo_addons/stock_inventory_discrepancy/i18n/pt_BR.po
odoo_addons/stock_inventory_discrepancy/i18n/sk.po
odoo_addons/stock_inventory_discrepancy/i18n/sl.po
odoo_addons/stock_inventory_discrepancy/i18n/stock_inventory_discrepancy.pot
odoo_addons/stock_inventory_discrepancy/i18n/tr_TR.po
odoo_addons/stock_inventory_discrepancy/models/__init__.py
odoo_addons/stock_inventory_discrepancy/models/stock_inventory.py
odoo_addons/stock_inventory_discrepancy/models/stock_inventory_line.py
odoo_addons/stock_inventory_discrepancy/models/stock_location.py
odoo_addons/stock_inventory_discrepancy/models/stock_warehouse.py
odoo_addons/stock_inventory_discrepancy/security/stock_inventory_discrepancy_security.xml
odoo_addons/stock_inventory_discrepancy/static/description/icon.png
odoo_addons/stock_inventory_discrepancy/tests/__init__.py
odoo_addons/stock_inventory_discrepancy/tests/test_inventory_discrepancy.py
odoo_addons/stock_inventory_discrepancy/views/stock_inventory_view.xml
odoo_addons/stock_inventory_discrepancy/views/stock_location_view.xml
odoo_addons/stock_inventory_discrepancy/views/stock_warehouse_view.xml
